zssh/__init__.py
zssh/__main__.py
zssh/zssh.py
zssh-1.2.0.dist-info/LICENSE
zssh-1.2.0.dist-info/METADATA
zssh-1.2.0.dist-info/WHEEL
zssh-1.2.0.dist-info/top_level.txt
zssh-1.2.0.dist-info/RECORD
