Metadata-Version: 2.1
Name: zssh
Version: 1.2.0
Summary: ZSSH - ZIP over SSH
Home-page: https://github.com/aslamanver/zssh
Author: Aslam Anver
Author-email: aslammohammedb@outlook.com
License: UNKNOWN
Platform: UNKNOWN
Classifier: Programming Language :: Python :: 3
Classifier: License :: OSI Approved :: MIT License
Classifier: Operating System :: OS Independent
Requires-Python: >=3.5
